dedalov2/__init__.py
dedalov2/blacklist.py
dedalov2/ddl.py
dedalov2/example.py
dedalov2/explanation.py
dedalov2/explanation_evaluation.py
dedalov2/knowledge_graph.py
dedalov2/linked_list.py
dedalov2/local_hdt.py
dedalov2/memory_profiler.py
dedalov2/path.py
dedalov2/path_evaluation.py
dedalov2/path_pruner.py
dedalov2/urishortener.py
dedalov2-0.0.2.dist-info/LICENSE
dedalov2-0.0.2.dist-info/METADATA
dedalov2-0.0.2.dist-info/WHEEL
dedalov2-0.0.2.dist-info/top_level.txt
dedalov2-0.0.2.dist-info/RECORD
