Metadata-Version: 2.1
Name: dedalov2
Version: 0.0.2
Summary: Explain groups of URIs on the Semantic Web
Home-page: https://github.com/jdonkervliet/dedalov2
Author: Jesse Donkervliet
Author-email: j.donkervliet+dedalo@gmail.com
License: UNKNOWN
Platform: UNKNOWN
Classifier: Programming Language :: Python :: 3
Classifier: License :: OSI Approved :: MIT License
Classifier: Operating System :: OS Independent
Requires-Python: >=3.7.2
Requires-Dist: hdt (>=2.2.1)
Requires-Dist: psutil (>=5.6.3)
